{"chunk_definitions":[{"row":14,"row_count":1,"visible":true,"expansion_state":0,"options":{"engine":"r","label":"unnamed-chunk-8","dev":"png"},"document_id":"95029171","chunk_id":"c1ahnsfm26ail","chunk_label":"unnamed-chunk-1"},{"row":46,"row_count":1,"visible":true,"expansion_state":0,"options":{"engine":"r","label":"unnamed-chunk-3","dev":"png"},"document_id":"95029171","chunk_id":"cbpwxfo15v7sj","chunk_label":"unnamed-chunk-2"},{"row":85,"row_count":1,"visible":true,"expansion_state":0,"options":{"engine":"r","label":"unnamed-chunk-6","dev":"png"},"document_id":"95029171","chunk_id":"cwzp09x91t5xq","chunk_label":"unnamed-chunk-4"},{"row":123,"row_count":1,"visible":true,"expansion_state":0,"options":{"engine":"r","label":"unnamed-chunk-23","dev":"png"},"document_id":"95029171","chunk_id":"cnbupeccg66lk","chunk_label":"unnamed-chunk-5"},{"row":201,"row_count":1,"visible":true,"expansion_state":0,"options":{"engine":"r","label":"unnamed-chunk-41","dev":"png"},"document_id":"95029171","chunk_id":"c70ws7whukrz6","chunk_label":"unnamed-chunk-6"},{"row":261,"row_count":1,"visible":true,"expansion_state":0,"options":{"engine":"r","label":"unnamed-chunk-73","dev":"png"},"document_id":"95029171","chunk_id":"ctjzufw9y36j1","chunk_label":"unnamed-chunk-7"},{"row":272,"row_count":1,"visible":true,"expansion_state":0,"options":{"engine":"r","label":"unnamed-chunk-12","dev":"png"},"document_id":"95029171","chunk_id":"cdztldnx9yqi8","chunk_label":"unnamed-chunk-8"},{"row":342,"row_count":1,"visible":true,"expansion_state":0,"options":{"engine":"r","label":"unnamed-chunk-53","dev":"png"},"document_id":"95029171","chunk_id":"cwbh2nlvl21n3","chunk_label":"unnamed-chunk-9"},{"row":399,"row_count":1,"visible":true,"expansion_state":0,"options":{"engine":"r","label":"unnamed-chunk-47","dev":"png"},"document_id":"95029171","chunk_id":"cyqa8087uwft1","chunk_label":"unnamed-chunk-10"}],"doc_write_time":1744926143}